{
  "tags": [
    {
      "id": 1,
      "route": "BLUE",
      "number": 1,
      "location": "ChargePoint charging station",
      "reward": "B",
      "nextLocationRiddle": "Find the beasts we love but sneeze at—where kibble is king.",
      "nextLocation": "Only Natural Pet",
      "passphraseRiddle": "Ask the data intern who touched lithium—enter their hometown.",
      "passphrase": "Fremont",
      "character": "Maya"
    },
    {
      "id": 2,
      "route": "BLUE",
      "number": 2,
      "location": "Only Natural Pet",
      "reward": "L",
      "nextLocationRiddle": "Water carves numbers—seek the stones where the river forgets its bed.",
      "nextLocation": "River bed",
      "passphraseRiddle": "Who sneezes near cats and swears by a 4-letter search tool? Type it.",
      "passphrase": "grep",
      "character": "Jeb Davis"
    },
    {
      "id": 3,
      "route": "BLUE",
      "number": 3,
      "location": "River bed",
      "reward": "U",
      "nextLocationRiddle": "Where logs talk and metrics sing—our data found a home.",
      "nextLocation": "Splunk Boulder",
      "passphraseRiddle": "The product lead who quotes murals—enter their first team codename.",
      "passphrase": "Pallas",
      "character": "Julia Wall"
    },
    {
      "id": 4,
      "route": "BLUE",
      "number": 4,
      "location": "Splunk Boulder",
      "reward": "E",
      "nextLocationRiddle": "Count stars indoors; a café named for the constellation.",
      "nextLocation": "Cassiopeia Café",
      "passphraseRiddle": "Ops' first love is a search; type the four letters.",
      "passphrase": "grep",
      "character": "Jeb Davis"
    },
    {
      "id": 5,
      "route": "BLUE",
      "number": 5,
      "location": "Cassiopeia Café",
      "reward": "R",
      "nextLocationRiddle": "Don't liege without one—seek the sweet subsection.",
      "nextLocation": "Waffles sub-spot",
      "passphraseRiddle": "Ask the marketer with the Belgian friend—what word comes before waffles?",
      "passphrase": "Liège",
      "character": "Lala Anson"
    },
    {
      "id": 6,
      "route": "BLUE",
      "number": 6,
      "location": "Waffles sub-spot",
      "reward": "O",
      "nextLocationRiddle": "Chirp if you must—find the old bird where a logo once perched.",
      "nextLocation": "Twitter logo sign",
      "passphraseRiddle": "Which exec's first job pulled shots? Enter their favorite drink.",
      "passphrase": "cortado",
      "character": "Opal Milota"
    },
    {
      "id": 7,
      "route": "BLUE",
      "number": 7,
      "location": "Park with 4 orange benches",
      "reward": "U",
      "nextLocationRiddle": "Where many paths meet—find the commons.",
      "nextLocation": "Boulder Commons",
      "passphraseRiddle": "Design nerd knows the orange—enter the Pantone number.",
      "passphrase": "1585",
      "character": "Zarin Saife"
    },
    {
      "id": 8,
      "route": "BLUE",
      "number": 8,
      "location": "Boulder Commons",
      "reward": "T",
      "nextLocationRiddle": "Climb the day—see the city through panes.",
      "nextLocation": "Glass stairway",
      "passphraseRiddle": "Legal's favorite duty from the murals—write it.",
      "passphrase": "NEIGHBORLY",
      "character": "Sarah Shaw"
    },
    {
      "id": 9,
      "route": "BLUE",
      "number": 9,
      "location": "Glass stairway",
      "reward": "E",
      "nextLocationRiddle": "Numbers await where streets converge; make for the address we all whisper.",
      "nextLocation": "2445 Junction Place",
      "passphraseRiddle": "Who maps every stair? Enter their surname.",
      "passphrase": "Calloway",
      "character": "Avery Calloway"
    },
    {
      "id": 10,
      "route": "BLUE",
      "number": 10,
      "location": "2445 Junction Place (Blue terminal)",
      "reward": "2",
      "nextLocationRiddle": "BLUE route complete—assemble at final when GOLD is done.",
      "nextLocation": "Final regroup",
      "passphraseRiddle": "Ask the CEO where they grew up.",
      "passphrase": "Reno",
      "character": "Opal Milota"
    },
    {
      "id": 11,
      "route": "GOLD",
      "number": 1,
      "location": "Boulder Kung Fu academy",
      "reward": "G",
      "nextLocationRiddle": "Numbers, forms, audits—where returns return.",
      "nextLocation": "Arkose Tax & Consulting",
      "passphraseRiddle": "Security learned from a mentor—type the mentor's title + letter.",
      "passphrase": "SIFU K",
      "character": "Elena Rodriguez"
    },
    {
      "id": 12,
      "route": "GOLD",
      "number": 2,
      "location": "Arkose Tax & Consulting",
      "reward": "O",
      "nextLocationRiddle": "Foam and beans at the log of legends.",
      "nextLocation": "Logan's Espresso Café",
      "passphraseRiddle": "Finance still remembers their auditor's surname—enter it.",
      "passphrase": "Arkady",
      "character": "Calvin Bonomo"
    },
    {
      "id": 13,
      "route": "GOLD",
      "number": 3,
      "location": "Logan's Espresso Café",
      "reward": "L",
      "nextLocationRiddle": "Skin-deep signage where SPF reigns.",
      "nextLocation": "Vasa Skin Solutions",
      "passphraseRiddle": "Whose favorite tee says four letters that mean 'you ain't gonna need it'? Enter the motto.",
      "passphrase": "YAGNI",
      "character": "Andrew Widner"
    },
    {
      "id": 14,
      "route": "GOLD",
      "number": 4,
      "location": "Vasa Skin Solutions",
      "reward": "D",
      "nextLocationRiddle": "Pedals and chains: the hard room.",
      "nextLocation": "Bike room (hard)",
      "passphraseRiddle": "Security's favorite number for sun.",
      "passphrase": "50",
      "passphraseAlt": "SPF50",
      "character": "Elena Rodriguez"
    },
    {
      "id": 15,
      "route": "GOLD",
      "number": 5,
      "location": "Bike room (hard)",
      "reward": "R",
      "nextLocationRiddle": "Painted promises: read the walls of three.",
      "nextLocation": "Three murals wall",
      "passphraseRiddle": "CTO's martial pastime in two words.",
      "passphrase": "Wing Chun",
      "character": "Conall Soon"
    },
    {
      "id": 16,
      "route": "GOLD",
      "number": 6,
      "location": "Three murals wall",
      "reward": "O",
      "nextLocationRiddle": "Find where paths intersect in title, not in track.",
      "nextLocation": "Junction sign",
      "passphraseRiddle": "Type the one word the product lead quotes from these.",
      "passphrase": "UNITY",
      "character": "Julia Wall"
    },
    {
      "id": 17,
      "route": "GOLD",
      "number": 7,
      "location": "Junction sign",
      "reward": "U",
      "nextLocationRiddle": "A counsel's porch you may not cross—observe from the curb.",
      "nextLocation": "Meredith House (outside)",
      "passphraseRiddle": "Legal's mnemonic for duty—write it.",
      "passphrase": "NEIGHBORLY",
      "character": "Sarah Johnson"
    },
    {
      "id": 18,
      "route": "GOLD",
      "number": 8,
      "location": "Meredith House (outside)",
      "reward": "T",
      "nextLocationRiddle": "A big sitting area: white stone shapes await.",
      "nextLocation": "Big sitting area (white stone benches)",
      "passphraseRiddle": "Type the owner's surname.",
      "passphrase": "Johnson",
      "character": "Sarah Johnson"
    },
    {
      "id": 19,
      "route": "GOLD",
      "number": 9,
      "location": "Big sitting area (white stone benches)",
      "reward": "E",
      "nextLocationRiddle": "Steel and glass, parked prestige.",
      "nextLocation": "Volvo XC90 (outside)",
      "passphraseRiddle": "Which routes lead loves this car? Enter the make.",
      "passphrase": "Volvo",
      "character": "Avery Calloway"
    },
    {
      "id": 20,
      "route": "GOLD",
      "number": 10,
      "location": "Volvo XC90 (outside)",
      "reward": "5",
      "nextLocationRiddle": "GOLD route complete—assemble at final.",
      "nextLocation": "Final regroup",
      "passphraseRiddle": "Enter the model.",
      "passphrase": "XC90",
      "character": null
    }
  ]
}
